[
  {
    "descrizione": "Solaio in laterocemento sp. 12cm",
    "costo_nuovo": 90.00,
    "unita": "mq"
  },
  {
    "descrizione": "Pilastro in acciaio HE300B",
    "costo_kg": 2.80,
    "unita": "kg",
    "densita_kg_m3": 7850
  },
  {
    "descrizione": "Trave HEB 100 in acciaio S275",
    "costo_kg": 2.60,
    "unita": "kg",
    "densita_kg_m3": 7850
  },
  {
    "descrizione": "Trave HEB 200 in acciaio S275",
    "costo_kg": 2.50,
    "unita": "kg",
    "densita_kg_m3": 7850
  },
  {
    "descrizione": "Trave HEB 300 in acciaio S275",
    "costo_kg": 2.35,
    "unita": "kg",
    "densita_kg_m3": 7850
  },
  {
    "descrizione": "Trave in cemento armato 62x90 cm",
    "costo_nuovo": 70.00,
    "unita": "ml"
  },
  {
    "descrizione": "Pilastro in acciaio HE300B (DEMOLIZIONE)",
    "costo_demolizione_kg": 0.75,
    "unita": "kg",
    "densita_kg_m3": 7850
  }
]
